<annotation>
	<folder>Fotos mates</folder>
	<filename>mamarkosich-17.jpeg</filename>
	<path>/Users/mariaagustinamarkosich/Documents/Facultad/Robots/Fotos mates/mamarkosich-17.jpeg</path>
	<source>
		<database>Unknown</database>
	</source>
	<size>
		<width>828</width>
		<height>785</height>
		<depth>3</depth>
	</size>
	<segmented>0</segmented>
	<object>
		<name>mate</name>
		<pose>Unspecified</pose>
		<truncated>0</truncated>
		<difficult>0</difficult>
		<bndbox>
			<xmin>202</xmin>
			<ymin>109</ymin>
			<xmax>562</xmax>
			<ymax>612</ymax>
		</bndbox>
	</object>
	<object>
		<name>calabaza</name>
		<pose>Unspecified</pose>
		<truncated>0</truncated>
		<difficult>0</difficult>
		<bndbox>
			<xmin>205</xmin>
			<ymin>111</ymin>
			<xmax>560</xmax>
			<ymax>621</ymax>
		</bndbox>
	</object>
</annotation>
